{
  "default": {
    "id": "default",
    "name": "深圳奇士美标准问答包",
    "description": "深圳奇士美油漆业务标准问答模板",
    "opening_line": "您好这里是深圳奇士美油漆，欢迎订购！请问您是哪个购买单位呢？",
    "qa_pairs": [
      {
        "question": "你们有什么油漆产品？",
        "answer": "我们主要经营各类工业油漆、木器漆、防腐漆等，请问您需要哪种类型的产品？"
      },
      {
        "question": "价格怎么样？",
        "answer": "我们的产品价格根据不同规格和数量有所不同，请问您需要多少量呢？我可以给您详细报价。"
      },
      {
        "question": "可以送货吗？",
        "answer": "可以的，我们提供送货上门服务，请问您的收货地址是哪里？"
      },
      {
        "question": "有现货吗？",
        "answer": "大部分产品都有现货，请问您具体需要什么产品？我帮您确认库存情况。"
      }
    ],
    "created_at": "2026-03-30",
    "updated_at": "2026-03-30"
  }
}
// 4243342